<?xml version="1.0" encoding="utf-8" ?>
<List>
  <Group>
    <Name>Lookup</Name>
    <Id>LOK</Id>
    <Items>
      <Item>
        <Id>LOK_Area_Res</Id>
        <Title>Areas</Title>
        <Controller>Area</Controller>
      </Item>
      <Item>
        <Id>LOK_Language_Res</Id>
        <Title>Languages</Title>
        <Controller>Language</Controller>
      </Item>    
    </Items>
  </Group>
  <Group>
    <Name>Modules</Name>
    <Id>MOD</Id>
    <Items>
      <Item>
        <Id>MOD_Class_Res</Id>
        <Title>Classes</Title>
        <Controller>StudyClass</Controller>
      </Item>
      <Item>
        <Id>MOD_Material_Res</Id>
        <Title>Materials</Title>
        <Controller>Material</Controller>
      </Item>
      <Item>
        <Id>MOD_Season_Res</Id>
        <Title>Seasons</Title>
        <Controller>Season</Controller>
      </Item>
      <Item>
        <Id>MOD_Section_Res</Id>
        <Title>Sections</Title>
        <Controller>Section</Controller>
      </Item>
      <Item>
        <Id>MOD_ExamTemplate_Res</Id>
        <Title>ExamTemplates</Title>
        <Controller>ExamTemplate</Controller>
      </Item>
      <Item>
        <Id>MOD_ExamTemplateItem_Res</Id>
        <Title>ExamTemplateItems</Title>
        <Controller>ExamTemplateItem</Controller>
      </Item>
    </Items>
  </Group>
</List>